bloopy/__init__.py
bloopy/individual.py
bloopy/mutation_functions.py
bloopy/reproductive_functions.py
bloopy/selection_functions.py
bloopy/utils.py
bloopy/algorithms/__init__.py
bloopy/algorithms/basin_hopping.py
bloopy/algorithms/continuous_base.py
bloopy/algorithms/differential_evolution.py
bloopy/algorithms/discrete_diffevo.py
bloopy/algorithms/dual_annealing.py
bloopy/algorithms/genetic_algorithm.py
bloopy/algorithms/genetic_local_search.py
bloopy/algorithms/hillclimbers.py
bloopy/algorithms/iterative_local_search.py
bloopy/algorithms/local_minimize.py
bloopy/algorithms/local_search.py
bloopy/algorithms/ltga.py
bloopy/algorithms/ltga_greedy.py
bloopy/algorithms/pso_pyswarms.py
bloopy/algorithms/random_sampling.py
bloopy/algorithms/simulated_annealing.py
bloopy/algorithms/tabu_search.py
bloopy/analysis/FFG.py
bloopy/analysis/__init__.py
bloopy/analysis/analysis_utils.py
bloopy/analysis/critical_points.py
bloopy/tests/__init__.py
bloopy/tests/test_bitstring.py
bloopy/tests/test_indiv.py
bloopy-0.4.2.dist-info/METADATA
bloopy-0.4.2.dist-info/WHEEL
bloopy-0.4.2.dist-info/top_level.txt
bloopy-0.4.2.dist-info/RECORD
