Metadata-Version: 2.1
Name: bloopy
Version: 0.4.2
Summary: BlooPy: Black-box optimization Python for bitstring, categorical, and numerical discrete problems with local, and population-based algorithms.
Home-page: https://github.com/schoonhovenrichard/BlooPy
Author: Richard Schoonhoven
Author-email: r.a.schoonhoven@hotmail.com
License: UNKNOWN
Download-URL: https://github.com/schoonhovenrichard/BlooPy/archive/refs/tags/0.4.2.tar.gz
Keywords: auto-tuning,optimization,gradient-free,black-box,computing,algorithms,discrete,minimization,maximization,evolutionary,fitness
Platform: UNKNOWN
Requires-Dist: numpy (>=1.19.0)
Requires-Dist: scipy (>=1.6.0)
Requires-Dist: bitarray
Requires-Dist: pyswarms
Requires-Dist: networkx
Requires-Dist: pytest
Requires-Dist: hypothesis
